HISTORY.rst
LICENSE
MANIFEST.in
NOTICE
README.rst
requirements.txt
run.py
setup.cfg
setup.py
strikepackage/__init__.py
strikepackage/__main__.py
strikepackage/config.py
strikepackage/engage.py
strikepackage/mchm.py
strikepackage/puppet.py
strikepackage/strikepackage.py
strikepackage/utils.py
strikepackage/xenserver.py
strikepackage.egg-info/PKG-INFO
strikepackage.egg-info/SOURCES.txt
strikepackage.egg-info/dependency_links.txt
strikepackage.egg-info/entry_points.txt
strikepackage.egg-info/not-zip-safe
strikepackage.egg-info/requires.txt
strikepackage.egg-info/top_level.txt
strikepackage/examples/__init__.py
strikepackage/examples/config.yaml
strikepackage/examples/metadata.jinja2
strikepackage/examples/userdata.jinja2
strikepackage/packages/__init__.py
strikepackage/packages/provision.py