Metadata-Version: 1.1
Name: strikepackage
Version: 0.5.3
Summary: A command line tool to deploy virtual machines on XenServer.
Home-page: https://github.com/pwyliu/strikepackage
Author: Paul Liu
Author-email: paul@ferociouspings.com
License: MIT
Keywords: XenServer XenAPI virtualization automation
Platform: UNKNOWN
Classifier: Development Status :: 3 - Alpha
Classifier: Intended Audience :: System Administrators
Classifier: Topic :: System :: Systems Administration
Classifier: License :: OSI Approved :: MIT License
Classifier: Programming Language :: Python :: 2.7
Classifier: Programming Language :: Python :: 2 :: Only
Classifier: Operating System :: POSIX :: Linux
